chip/ChipUtility.py
chip/clusters/CHIPClusters.py
chip/clusters/ClusterObjects.py
chip/clusters/Objects.py
chip/clusters/TestObjects.py
chip/clusters/Types.py
chip/clusters/enum.py
chip/tlv/__init__.py
chip/tlv/tlvlist.py
home_assistant_chip_clusters-2025.4.0.dist-info/LICENSE
home_assistant_chip_clusters-2025.4.0.dist-info/METADATA
home_assistant_chip_clusters-2025.4.0.dist-info/WHEEL
home_assistant_chip_clusters-2025.4.0.dist-info/top_level.txt
home_assistant_chip_clusters-2025.4.0.dist-info/RECORD
